{
  "navigation": {
    "home": "Home",
    "hurghada-excursions": "hurghada excursions",
    "about": "About",
    "contact": "Contact"
  },
  "hero": {
    "imageAlt": "Red Sea tours in Sharm El Sheikh and Hurghada",
    "badge": "Best Travel Destinations in Egypt",
    "titleBefore": "Top Excursions in",
    "hurghada": "Hurghada",
    "sharm": "Sharm El Sheikh",
    "subtitle": "Best Things to Do in Egypt's Top Resorts",
    "paragraph": "Hurghada Excursions, Desert Safaris & Red Sea Adventures with Horizonica Travel – Explore Egypt's Best Beach Holidays and Tailored Tours",
    "bookNow": "Book Now",
    "learnMore": "Learn More About Us"
  }
}
